LICENSE.txt
README.md
setup.cfg
setup.py
yaypm/__init__.py
yaypm/flow.py
yaypm3.egg-info/PKG-INFO
yaypm3.egg-info/SOURCES.txt
yaypm3.egg-info/dependency_links.txt
yaypm3.egg-info/requires.txt
yaypm3.egg-info/top_level.txt
yaypm/examples/__init__.py
yaypm/examples/keyecho.py
yaypm/examples/keyecho2.py
yaypm/examples/pbx.py
yaypm/utils/__init__.py
yaypm/utils/answer.py
yaypm/utils/srcmon.py
yaypm/utils/resources/__init__.py
yaypm/utils/tester/__init__.py
yaypm/utils/tester/dtmfetc.py